LICENSE
MANIFEST.in
README.md
setup.py
jtalkpy/__init__.py
jtalkpy.egg-info/PKG-INFO
jtalkpy.egg-info/SOURCES.txt
jtalkpy.egg-info/dependency_links.txt
jtalkpy.egg-info/top_level.txt