Metadata-Version: 2.1
Name: jtalkpy
Version: 1.0.0
Summary: Python rapper module of open_jtalk
Home-page: https://github.com/yhay81/jtalkpy
Author: Yusuke Hayashi
Author-email: yusuke8h@gmail.com
License: MIT
Platform: UNKNOWN
Classifier: License :: OSI Approved :: MIT License
Classifier: Programming Language :: Python
Classifier: Programming Language :: Python :: 3
Classifier: Programming Language :: Python :: Implementation :: CPython
Classifier: Programming Language :: Python :: Implementation :: PyPy
Requires-Python: >=3.5.0
